{
  "type": "minecraft:crafting_shapeless",
  "ingredients": [
    {
      "item": "steeringlawstudy:ruby"
    },
    {
      "item": "steeringlawstudy:ruby"
    },
    {
      "item": "steeringlawstudy:ruby"
    },
    {
      "item": "steeringlawstudy:ruby"
    },
    {
      "item": "steeringlawstudy:ruby"
    },
    {
      "item": "steeringlawstudy:ruby"
    },
    {
      "item": "steeringlawstudy:ruby"
    },
    {
      "item": "steeringlawstudy:ruby"
    },
    {
      "item": "steeringlawstudy:ruby"
    }
  ],
  "result":
  {
    "item": "steeringlawstudy:ruby_block",
    "count": 1
  }
}